{
    "meta": {
        "total_pages": 5,
        "panels_per_page": 6,
        "total_panels": 30,
        "page_aspect": "9:16",
        "coord_w": 1000.0,
        "coord_h": 1777.7777777777778,
        "generated_at": "2026-04-17T12:05:37"
    },
    "pages": [
        {
            "page_number": 1,
            "panels_count": 6,
            "panels": [
                {
                    "global_order": 1,
                    "page_order": 1,
                    "page_number": 1,
                    "file_name": "page_001_panel_01.jpg",
                    "aspect_ratio": 0.8411,
                    "aspect_label": "tall_square",
                    "width_ratio": 0.496417,
                    "height_ratio": 0.331985,
                    "bbox": {
                        "x": 4.0,
                        "y": 4.0,
                        "w": 496.4171,
                        "h": 590.196
                    },
                    "vertices": [
                        [
                            4.0,
                            4.0
                        ],
                        [
                            500.4171,
                            4.0
                        ],
                        [
                            500.4171,
                            594.196
                        ],
                        [
                            4.0,
                            594.196
                        ]
                    ]
                },
                {
                    "global_order": 2,
                    "page_order": 2,
                    "page_number": 1,
                    "file_name": "page_001_panel_02.jpg",
                    "aspect_ratio": 0.8227,
                    "aspect_label": "tall_square",
                    "width_ratio": 0.485583,
                    "height_ratio": 0.331985,
                    "bbox": {
                        "x": 510.4171,
                        "y": 4.0,
                        "w": 485.5829,
                        "h": 590.196
                    },
                    "vertices": [
                        [
                            510.4171,
                            4.0
                        ],
                        [
                            996.0,
                            4.0
                        ],
                        [
                            996.0,
                            594.196
                        ],
                        [
                            510.4171,
                            594.196
                        ]
                    ]
                },
                {
                    "global_order": 3,  
                    "page_order": 3,
                    "page_number": 1,
                    "file_name": "page_001_panel_03.jpg",
                    "aspect_ratio": 0.8251,
                    "aspect_label": "tall_square",
                    "width_ratio": 0.478969,
                    "height_ratio": 0.326539,
                    "bbox": {
                        "x": 4.0,
                        "y": 604.196,
                        "w": 478.9694,
                        "h": 580.5133
                    },
                    "vertices": [
                        [
                            4.0,
                            604.196
                        ],
                        [
                            482.9694,
                            604.196
                        ],
                        [
                            482.9694,
                            1184.7093
                        ],
                        [
                            4.0,
                            1184.7093
                        ]
                    ]
                },
                {
                    "global_order": 4,
                    "page_order": 4,
                    "page_number": 1,
                    "file_name": "page_001_panel_04.jpg",
                    "aspect_ratio": 0.8665,
                    "aspect_label": "tall_square",
                    "width_ratio": 0.503031,
                    "height_ratio": 0.326539,
                    "bbox": {
                        "x": 492.9694,
                        "y": 604.196,
                        "w": 503.0306,
                        "h": 580.5133
                    },
                    "vertices": [
                        [
                            492.9694,
                            604.196
                        ],
                        [
                            996.0,
                            604.196
                        ],
                        [
                            996.0,
                            1184.7093
                        ],
                        [
                            492.9694,
                            1184.7093
                        ]
                    ]
                },
                {
                    "global_order": 5,
                    "page_order": 5,
                    "page_number": 1,
                    "file_name": "page_001_panel_05.jpg",
                    "aspect_ratio": 0.8468,
                    "aspect_label": "tall_square",
                    "width_ratio": 0.490347,
                    "height_ratio": 0.325726,
                    "bbox": {
                        "x": 4.0,
                        "y": 1194.7093,
                        "w": 490.3473,
                        "h": 579.0685
                    },
                    "vertices": [
                        [
                            4.0,
                            1194.7093
                        ],
                        [
                            494.3473,
                            1194.7093
                        ],
                        [
                            494.3473,
                            1773.7778
                        ],
                        [
                            4.0,
                            1773.7778
                        ]
                    ]
                },
                {
                    "global_order": 6,
                    "page_order": 6,
                    "page_number": 1,
                    "file_name": "page_001_panel_06.jpg",
                    "aspect_ratio": 0.849,
                    "aspect_label": "tall_square",
                    "width_ratio": 0.491653,
                    "height_ratio": 0.325726,
                    "bbox": {
                        "x": 504.3473,
                        "y": 1194.7093,
                        "w": 491.6527,
                        "h": 579.0685
                    },
                    "vertices": [
                        [
                            504.3473,
                            1194.7093
                        ],
                        [
                            996.0,
                            1194.7093
                        ],
                        [
                            996.0,
                            1773.7778
                        ],
                        [
                            504.3473,
                            1773.7778
                        ]
                    ]
                }
            ]
        },
        {
            "page_number": 2,
            "panels_count": 6,
            "panels": [
                {
                    "global_order": 7,
                    "page_order": 1,
                    "page_number": 2,
                    "file_name": "page_002_panel_01.jpg",
                    "aspect_ratio": 1.1081,
                    "aspect_label": "wide_square",
                    "width_ratio": 0.491252,
                    "height_ratio": 0.24937,
                    "bbox": {
                        "x": 4.0,
                        "y": 4.0,
                        "w": 491.252,
                        "h": 443.3242
                    },
                    "vertices": [
                        [
                            4.0,
                            4.0
                        ],
                        [
                            495.252,
                            4.0
                        ],
                        [
                            495.252,
                            447.3242
                        ],
                        [
                            4.0,
                            447.3242
                        ]
                    ]
                },
                {
                    "global_order": 8,
                    "page_order": 2,
                    "page_number": 2,
                    "file_name": "page_002_panel_02.jpg",
                    "aspect_ratio": 1.107,
                    "aspect_label": "wide_square",
                    "width_ratio": 0.490748,
                    "height_ratio": 0.24937,
                    "bbox": {
                        "x": 505.252,
                        "y": 4.0,
                        "w": 490.748,
                        "h": 443.3242
                    },
                    "vertices": [
                        [
                            505.252,
                            4.0
                        ],
                        [
                            996.0,
                            4.0
                        ],
                        [
                            996.0,
                            447.3242
                        ],
                        [
                            505.252,
                            447.3242
                        ]
                    ]
                },
                {
                    "global_order": 9,
                    "page_order": 3,
                    "page_number": 2,
                    "file_name": "page_002_panel_03.jpg",
                    "aspect_ratio": 1.1274,
                    "aspect_label": "wide_square",
                    "width_ratio": 0.500182,
                    "height_ratio": 0.249567,
                    "bbox": {
                        "x": 4.0,
                        "y": 457.3242,
                        "w": 500.1818,
                        "h": 443.6741
                    },
                    "vertices": [
                        [
                            4.0,
                            457.3242
                        ],
                        [
                            504.1818,
                            457.3242
                        ],
                        [
                            504.1818,
                            900.9983
                        ],
                        [
                            4.0,
                            900.9983
                        ]
                    ]
                },
                {
                    "global_order": 10,
                    "page_order": 4,
                    "page_number": 2,
                    "file_name": "page_002_panel_04.jpg",
                    "aspect_ratio": 1.086,
                    "aspect_label": "wide_square",
                    "width_ratio": 0.481818,
                    "height_ratio": 0.249567,
                    "bbox": {
                        "x": 514.1818,
                        "y": 457.3242,
                        "w": 481.8182,
                        "h": 443.6741
                    },
                    "vertices": [
                        [
                            514.1818,
                            457.3242
                        ],
                        [
                            996.0,
                            457.3242
                        ],
                        [
                            996.0,
                            900.9983
                        ],
                        [
                            514.1818,
                            900.9983
                        ]
                    ]
                },
                {
                    "global_order": 11,
                    "page_order": 5,
                    "page_number": 2,
                    "file_name": "page_002_panel_05.jpg",
                    "aspect_ratio": 0.5757,
                    "aspect_label": "tall_portrait",
                    "width_ratio": 0.496724,
                    "height_ratio": 0.485313,
                    "bbox": {
                        "x": 4.0,
                        "y": 910.9983,
                        "w": 496.724,
                        "h": 862.7795
                    },
                    "vertices": [
                        [
                            4.0,
                            910.9983
                        ],
                        [
                            500.724,
                            910.9983
                        ],
                        [
                            500.724,
                            1773.7778
                        ],
                        [
                            4.0,
                            1773.7778
                        ]
                    ]
                },
                {
                    "global_order": 12,
                    "page_order": 6,
                    "page_number": 2,
                    "file_name": "page_002_panel_06.jpg",
                    "aspect_ratio": 0.5625,
                    "aspect_label": "tall_portrait",
                    "width_ratio": 0.485276,
                    "height_ratio": 0.485313,
                    "bbox": {
                        "x": 510.724,
                        "y": 910.9983,
                        "w": 485.276,
                        "h": 862.7795
                    },
                    "vertices": [
                        [
                            510.724,
                            910.9983
                        ],
                        [
                            996.0,
                            910.9983
                        ],
                        [
                            996.0,
                            1773.7778
                        ],
                        [
                            510.724,
                            1773.7778
                        ]
                    ]
                }
            ]
        },
        {
            "page_number": 3,
            "panels_count": 6,
            "panels": [
                {
                    "global_order": 13,
                    "page_order": 1,
                    "page_number": 3,
                    "file_name": "page_003_panel_01.jpg",
                    "aspect_ratio": 0.8626,
                    "aspect_label": "tall_square",
                    "width_ratio": 0.489841,
                    "height_ratio": 0.319416,
                    "bbox": {
                        "x": 4.0,
                        "y": 4.0,
                        "w": 489.8409,
                        "h": 567.8511
                    },
                    "vertices": [
                        [
                            4.0,
                            4.0
                        ],
                        [
                            493.8409,
                            4.0
                        ],
                        [
                            493.8409,
                            571.8511
                        ],
                        [
                            4.0,
                            571.8511
                        ]
                    ]
                },
                {
                    "global_order": 14,
                    "page_order": 2,
                    "page_number": 3,
                    "file_name": "page_003_panel_02.jpg",
                    "aspect_ratio": 0.8667,
                    "aspect_label": "tall_square",
                    "width_ratio": 0.492159,
                    "height_ratio": 0.319416,
                    "bbox": {
                        "x": 503.8409,
                        "y": 4.0,
                        "w": 492.1591,
                        "h": 567.8511
                    },
                    "vertices": [
                        [
                            503.8409,
                            4.0
                        ],
                        [
                            996.0,
                            4.0
                        ],
                        [
                            996.0,
                            571.8511
                        ],
                        [
                            503.8409,
                            571.8511
                        ]
                    ]
                },
                {
                    "global_order": 15,
                    "page_order": 3,
                    "page_number": 3,
                    "file_name": "page_003_panel_03.jpg",
                    "aspect_ratio": 0.8583,
                    "aspect_label": "tall_square",
                    "width_ratio": 0.495721,
                    "height_ratio": 0.324869,
                    "bbox": {
                        "x": 4.0,
                        "y": 581.8511,
                        "w": 495.7211,
                        "h": 577.5443
                    },
                    "vertices": [
                        [
                            4.0,
                            581.8511
                        ],
                        [
                            499.7211,
                            581.8511
                        ],
                        [
                            499.7211,
                            1159.3953
                        ],
                        [
                            4.0,
                            1159.3953
                        ]
                    ]
                },
                {
                    "global_order": 16,
                    "page_order": 4,
                    "page_number": 3,
                    "file_name": "page_003_panel_04.jpg",
                    "aspect_ratio": 0.842,
                    "aspect_label": "tall_square",
                    "width_ratio": 0.486279,
                    "height_ratio": 0.324869,
                    "bbox": {
                        "x": 509.7211,
                        "y": 581.8511,
                        "w": 486.2789,
                        "h": 577.5443
                    },
                    "vertices": [
                        [
                            509.7211,
                            581.8511
                        ],
                        [
                            996.0,
                            581.8511
                        ],
                        [
                            996.0,
                            1159.3953
                        ],
                        [
                            509.7211,
                            1159.3953
                        ]
                    ]
                },
                {
                    "global_order": 17,
                    "page_order": 5,
                    "page_number": 3,
                    "file_name": "page_003_panel_05.jpg",
                    "aspect_ratio": 0.8152,
                    "aspect_label": "tall_square",
                    "width_ratio": 0.492683,
                    "height_ratio": 0.339965,
                    "bbox": {
                        "x": 4.0,
                        "y": 1169.3953,
                        "w": 492.6826,
                        "h": 604.3824
                    },
                    "vertices": [
                        [
                            4.0,
                            1169.3953
                        ],
                        [
                            496.6826,
                            1169.3953
                        ],
                        [
                            496.6826,
                            1773.7778
                        ],
                        [
                            4.0,
                            1773.7778
                        ]
                    ]
                },
                {
                    "global_order": 18,
                    "page_order": 6,
                    "page_number": 3,
                    "file_name": "page_003_panel_06.jpg",
                    "aspect_ratio": 0.8096,
                    "aspect_label": "tall_square",
                    "width_ratio": 0.489317,
                    "height_ratio": 0.339965,
                    "bbox": {
                        "x": 506.6826,
                        "y": 1169.3953,
                        "w": 489.3174,
                        "h": 604.3824
                    },
                    "vertices": [
                        [
                            506.6826,
                            1169.3953
                        ],
                        [
                            996.0,
                            1169.3953
                        ],
                        [
                            996.0,
                            1773.7778
                        ],
                        [
                            506.6826,
                            1773.7778
                        ]
                    ]
                }
            ]
        },
        {
            "page_number": 4,
            "panels_count": 6,
            "panels": [
                {
                    "global_order": 19,
                    "page_order": 1,
                    "page_number": 4,
                    "file_name": "page_004_panel_01.jpg",
                    "aspect_ratio": 2.3163,
                    "aspect_label": "panoramic",
                    "width_ratio": 0.992,
                    "height_ratio": 0.240902,
                    "bbox": {
                        "x": 4.0,
                        "y": 4.0,
                        "w": 992.0,
                        "h": 428.27
                    },
                    "vertices": [
                        [
                            4.0,
                            4.0
                        ],
                        [
                            996.0,
                            4.0
                        ],
                        [
                            996.0,
                            432.27
                        ],
                        [
                            4.0,
                            432.27
                        ]
                    ]
                },
                {
                    "global_order": 20,
                    "page_order": 2,
                    "page_number": 4,
                    "file_name": "page_004_panel_02.jpg",
                    "aspect_ratio": 1.0569,
                    "aspect_label": "wide_square",
                    "width_ratio": 0.47524,
                    "height_ratio": 0.252921,
                    "bbox": {
                        "x": 4.0,
                        "y": 442.27,
                        "w": 475.2398,
                        "h": 449.6369
                    },
                    "vertices": [
                        [
                            4.0,
                            442.27
                        ],
                        [
                            479.2398,
                            442.27
                        ],
                        [
                            479.2398,
                            891.9069
                        ],
                        [
                            4.0,
                            891.9069
                        ]
                    ]
                },
                {
                    "global_order": 21,
                    "page_order": 3,
                    "page_number": 4,
                    "file_name": "page_004_panel_03.jpg",
                    "aspect_ratio": 1.127,
                    "aspect_label": "wide_square",
                    "width_ratio": 0.50676,
                    "height_ratio": 0.252921,
                    "bbox": {
                        "x": 489.2398,
                        "y": 442.27,
                        "w": 506.7602,
                        "h": 449.6369
                    },
                    "vertices": [
                        [
                            489.2398,
                            442.27
                        ],
                        [
                            996.0,
                            442.27
                        ],
                        [
                            996.0,
                            891.9069
                        ],
                        [
                            489.2398,
                            891.9069
                        ]
                    ]
                },
                {
                    "global_order": 22,
                    "page_order": 4,
                    "page_number": 4,
                    "file_name": "page_004_panel_04.jpg",
                    "aspect_ratio": 1.1589,
                    "aspect_label": "wide_square",
                    "width_ratio": 0.491242,
                    "height_ratio": 0.238426,
                    "bbox": {
                        "x": 4.0,
                        "y": 901.9069,
                        "w": 491.2423,
                        "h": 423.8691
                    },
                    "vertices": [
                        [
                            4.0,
                            901.9069
                        ],
                        [
                            495.2423,
                            901.9069
                        ],
                        [
                            495.2423,
                            1325.776
                        ],
                        [
                            4.0,
                            1325.776
                        ]
                    ]
                },
                {
                    "global_order": 23,
                    "page_order": 5,
                    "page_number": 4,
                    "file_name": "page_004_panel_05.jpg",
                    "aspect_ratio": 1.1216,
                    "aspect_label": "wide_square",
                    "width_ratio": 0.491242,
                    "height_ratio": 0.246376,
                    "bbox": {
                        "x": 4.0,
                        "y": 1335.776,
                        "w": 491.2423,
                        "h": 438.0018
                    },
                    "vertices": [
                        [
                            4.0,
                            1335.776
                        ],
                        [
                            495.2423,
                            1335.776
                        ],
                        [
                            495.2423,
                            1773.7778
                        ],
                        [
                            4.0,
                            1773.7778
                        ]
                    ]
                },
                {
                    "global_order": 24,
                    "page_order": 6,
                    "page_number": 4,
                    "file_name": "page_004_panel_06.jpg",
                    "aspect_ratio": 0.5629,
                    "aspect_label": "tall_portrait",
                    "width_ratio": 0.490758,
                    "height_ratio": 0.490427,
                    "bbox": {
                        "x": 505.2423,
                        "y": 901.9069,
                        "w": 490.7577,
                        "h": 871.8709
                    },
                    "vertices": [
                        [
                            505.2423,
                            901.9069
                        ],
                        [
                            996.0,
                            901.9069
                        ],
                        [
                            996.0,
                            1773.7778
                        ],
                        [
                            505.2423,
                            1773.7778
                        ]
                    ]
                }
            ]
        },
        {
            "page_number": 5,
            "panels_count": 6,
            "panels": [
                {
                    "global_order": 25,
                    "page_order": 1,
                    "page_number": 5,
                    "file_name": "page_005_panel_01.jpg",
                    "aspect_ratio": 0.857,
                    "aspect_label": "tall_square",
                    "width_ratio": 0.491657,
                    "height_ratio": 0.322697,
                    "bbox": {
                        "x": 4.0,
                        "y": 4.0,
                        "w": 491.6569,
                        "h": 573.6844
                    },
                    "vertices": [
                        [
                            4.0,
                            4.0
                        ],
                        [
                            495.6569,
                            4.0
                        ],
                        [
                            495.6569,
                            577.6844
                        ],
                        [
                            4.0,
                            577.6844
                        ]
                    ]
                },
                {
                    "global_order": 26,
                    "page_order": 2,
                    "page_number": 5,
                    "file_name": "page_005_panel_02.jpg",
                    "aspect_ratio": 0.8547,
                    "aspect_label": "tall_square",
                    "width_ratio": 0.490343,
                    "height_ratio": 0.322697,
                    "bbox": {
                        "x": 505.6569,
                        "y": 4.0,
                        "w": 490.3431,
                        "h": 573.6844
                    },
                    "vertices": [
                        [
                            505.6569,
                            4.0
                        ],
                        [
                            996.0,
                            4.0
                        ],
                        [
                            996.0,
                            577.6844
                        ],
                        [
                            505.6569,
                            577.6844
                        ]
                    ]
                },
                {
                    "global_order": 27,
                    "page_order": 3,
                    "page_number": 5,
                    "file_name": "page_005_panel_03.jpg",
                    "aspect_ratio": 0.8286,
                    "aspect_label": "tall_square",
                    "width_ratio": 0.491647,
                    "height_ratio": 0.333771,
                    "bbox": {
                        "x": 4.0,
                        "y": 587.6844,
                        "w": 491.6469,
                        "h": 593.37
                    },
                    "vertices": [
                        [
                            4.0,
                            587.6844
                        ],
                        [
                            495.6469,
                            587.6844
                        ],
                        [
                            495.6469,
                            1181.0544
                        ],
                        [
                            4.0,
                            1181.0544
                        ]
                    ]
                },
                {
                    "global_order": 28,
                    "page_order": 4,
                    "page_number": 5,
                    "file_name": "page_005_panel_04.jpg",
                    "aspect_ratio": 0.8264,
                    "aspect_label": "tall_square",
                    "width_ratio": 0.490353,
                    "height_ratio": 0.333771,
                    "bbox": {
                        "x": 505.6469,
                        "y": 587.6844,
                        "w": 490.3531,
                        "h": 593.37
                    },
                    "vertices": [
                        [
                            505.6469,
                            587.6844
                        ],
                        [
                            996.0,
                            587.6844
                        ],
                        [
                            996.0,
                            1181.0544
                        ],
                        [
                            505.6469,
                            1181.0544
                        ]
                    ]
                },
                {
                    "global_order": 29,
                    "page_order": 5,
                    "page_number": 5,
                    "file_name": "page_005_panel_05.jpg",
                    "aspect_ratio": 0.8387,
                    "aspect_label": "tall_square",
                    "width_ratio": 0.488717,
                    "height_ratio": 0.327782,
                    "bbox": {
                        "x": 4.0,
                        "y": 1191.0544,
                        "w": 488.7175,
                        "h": 582.7234
                    },
                    "vertices": [
                        [
                            4.0,
                            1191.0544
                        ],
                        [
                            492.7175,
                            1191.0544
                        ],
                        [
                            492.7175,
                            1773.7778
                        ],
                        [
                            4.0,
                            1773.7778
                        ]
                    ]
                },
                {
                    "global_order": 30,
                    "page_order": 6,
                    "page_number": 5,
                    "file_name": "page_005_panel_06.jpg",
                    "aspect_ratio": 0.8465,
                    "aspect_label": "tall_square",
                    "width_ratio": 0.493283,
                    "height_ratio": 0.327782,
                    "bbox": {
                        "x": 502.7175,
                        "y": 1191.0544,
                        "w": 493.2825,
                        "h": 582.7234
                    },
                    "vertices": [
                        [
                            502.7175,
                            1191.0544
                        ],
                        [
                            996.0,
                            1191.0544
                        ],
                        [
                            996.0,
                            1773.7778
                        ],
                        [
                            502.7175,
                            1773.7778
                        ]
                    ]
                }
            ]
        }
    ]
}